calculator_package_swhitt_tc/__init__.py
calculator_package_swhitt_tc/calculator.py
calculator_package_swhitt_tc-0.0.1.dist-info/METADATA
calculator_package_swhitt_tc-0.0.1.dist-info/WHEEL
calculator_package_swhitt_tc-0.0.1.dist-info/licenses/LICENSE.lic
calculator_package_swhitt_tc-0.0.1.dist-info/RECORD
