Metadata-Version: 2.3
Name: calculator_package_swhitt_tc
Version: 0.0.1
Summary: A simple calculator application.
Author-email: Sydney Whittington <swhitt.tc@gmail.com>
License-File: LICENSE.lic
Classifier: License :: OSI Approved :: MIT License
Classifier: Operating System :: OS Independent
Classifier: Programming Language :: Python :: 3
Requires-Python: >=3.8
